MANIFEST.in
README.rst
setup.cfg
setup.py
testcec.py
cec2005real/CMakeLists.txt
cec2005real/Makefile
cec2005real/README.rst
cec2005real/__init__.py
cec2005real/api_cec2005.cc
cec2005real/aux.cc
cec2005real/cec2005.cc
cec2005real/cec2005.cpp
cec2005real/cec2005.h
cec2005real/cec2005.pyx
cec2005real/def1.cc
cec2005real/def2.cc
cec2005real/def3.cc
cec2005real/def4.cc
cec2005real/define.h
cec2005real/functions.cc
cec2005real/functions.h
cec2005real/global.h
cec2005real/newutil.cc
cec2005real/newutil.h
cec2005real/problemcec2005.h
cec2005real/problemeasy.h
cec2005real/rand.h
cec2005real/random.h
cec2005real/real.h
cec2005real/srandom.h
cec2005real/sub.h
cec2005real/test.cc
cec2005real.egg-info/PKG-INFO
cec2005real.egg-info/SOURCES.txt
cec2005real.egg-info/SOURCES.txt~
cec2005real.egg-info/dependency_links.txt
cec2005real.egg-info/pbr.json
cec2005real.egg-info/requires.txt
cec2005real.egg-info/top_level.txt
cec2005real/CMakeFiles/3.0.2/CompilerIdCXX/CMakeCXXCompilerId.cpp
cec2005real/cdatafiles/EF8F2_func_data.mat
cec2005real/cdatafiles/EF8F2_func_data.txt
cec2005real/cdatafiles/E_ScafferF6_M_D10.mat
cec2005real/cdatafiles/E_ScafferF6_M_D10.txt
cec2005real/cdatafiles/E_ScafferF6_M_D2.mat
cec2005real/cdatafiles/E_ScafferF6_M_D2.txt
cec2005real/cdatafiles/E_ScafferF6_M_D30.mat
cec2005real/cdatafiles/E_ScafferF6_M_D30.txt
cec2005real/cdatafiles/E_ScafferF6_M_D50.mat
cec2005real/cdatafiles/E_ScafferF6_M_D50.txt
cec2005real/cdatafiles/E_ScafferF6_func_data.mat
cec2005real/cdatafiles/E_ScafferF6_func_data.txt
cec2005real/cdatafiles/Files List and some explanation.txt
cec2005real/cdatafiles/Files List.txt
cec2005real/cdatafiles/ackley_M_D10.mat
cec2005real/cdatafiles/ackley_M_D10.txt
cec2005real/cdatafiles/ackley_M_D2.mat
cec2005real/cdatafiles/ackley_M_D2.txt
cec2005real/cdatafiles/ackley_M_D30.mat
cec2005real/cdatafiles/ackley_M_D30.txt
cec2005real/cdatafiles/ackley_M_D50.mat
cec2005real/cdatafiles/ackley_M_D50.txt
cec2005real/cdatafiles/ackley_func_data.mat
cec2005real/cdatafiles/ackley_func_data.txt
cec2005real/cdatafiles/elliptic_M_D10.mat
cec2005real/cdatafiles/elliptic_M_D10.txt
cec2005real/cdatafiles/elliptic_M_D2.mat
cec2005real/cdatafiles/elliptic_M_D2.txt
cec2005real/cdatafiles/elliptic_M_D30.mat
