Metadata-Version: 1.1
Name: cec2005real
Version: 0.1
Summary: Package for benchmark for the Real     Optimization session on IEEE     Congress on Evolutionary Computation CEC'2005
Home-page: https://github.com/dmolina/cec2005real
Author: Daniel Molina
Author-email: daniel.molina@uca.es
License: GPL V3
Platform: UNKNOWN
Classifier: Development Status :: 5 - Production/Stable
Classifier: License :: OSI Approved :: GNU General Public License v3 or later (GPLv3+)
